babase/__init__.py
babase/_accountv2.py
babase/_app.py
babase/_appcomponent.py
babase/_appconfig.py
babase/_appintent.py
babase/_appmode.py
babase/_appmodeselector.py
babase/_appsubsystem.py
babase/_apputils.py
babase/_assetmanager.py
babase/_asyncio.py
babase/_cloud.py
babase/_emptyappmode.py
babase/_env.py
babase/_error.py
babase/_general.py
babase/_hooks.py
babase/_keyboard.py
babase/_language.py
babase/_login.py
babase/_math.py
babase/_meta.py
babase/_net.py
babase/_plugin.py
babase/_text.py
babase/_workspace.py
babase/modutils.py
baclassic/__init__.py
baclassic/_accountv1.py
baclassic/_achievement.py
baclassic/_ads.py
baclassic/_analytics.py
baclassic/_appdelegate.py
baclassic/_benchmark.py
baclassic/_input.py
baclassic/_music.py
baclassic/_net.py
baclassic/_servermode.py
baclassic/_store.py
baclassic/_subsystem.py
baclassic/_tips.py
baclassic/_tournament.py
baclassic/macmusicapp.py
baclassic/osmusic.py
baenv.py
baplus/__init__.py
baplus/_hooks.py
baplus/_subsystem.py
bascenev1/__init__.py
bascenev1/_activity.py
bascenev1/_activitytypes.py
bascenev1/_actor.py
bascenev1/_appmode.py
bascenev1/_campaign.py
bascenev1/_collision.py
bascenev1/_coopgame.py
bascenev1/_coopsession.py
bascenev1/_debug.py
bascenev1/_dependency.py
bascenev1/_dualteamsession.py
bascenev1/_featureset.py
bascenev1/_freeforallsession.py
bascenev1/_gameactivity.py
bascenev1/_gameresults.py
bascenev1/_gameutils.py
bascenev1/_hooks.py
bascenev1/_level.py
bascenev1/_lobby.py
bascenev1/_map.py
bascenev1/_messages.py
bascenev1/_multiteamsession.py
bascenev1/_music.py
bascenev1/_nodeactor.py
bascenev1/_player.py
bascenev1/_playlist.py
bascenev1/_powerup.py
bascenev1/_profile.py
bascenev1/_score.py
bascenev1/_session.py
bascenev1/_settings.py
bascenev1/_stats.py
bascenev1/_team.py
bascenev1/_teamgame.py
bascenev1lib/__init__.py
bascenev1lib/activity/__init__.py
bascenev1lib/activity/coopjoin.py
bascenev1lib/activity/coopscore.py
bascenev1lib/activity/drawscore.py
badev-1.7.27.dist-info/LICENSE
badev-1.7.27.dist-info/METADATA
badev-1.7.27.dist-info/WHEEL
badev-1.7.27.dist-info/RECORD
