Metadata-Version: 2.1
Name: badev
Version: 1.7.27
Summary: The BombSquad Modding Helper
License: MIT
Author: Aeliux
Author-email: itsaeliux@gmail.com
Requires-Python: >=3.8,<4.0
Classifier: Development Status :: 5 - Production/Stable
Classifier: License :: OSI Approved :: MIT License
Classifier: Programming Language :: Python :: 3
Classifier: Programming Language :: Python :: 3.8
Classifier: Programming Language :: Python :: 3.9
Classifier: Programming Language :: Python :: 3.10
Classifier: Programming Language :: Python :: 3.11
Classifier: Topic :: Text Editors :: Integrated Development Environments (IDE)
